k9/__init__.py
k9/__main__.py
k9/apps.py
k9/batch.py
k9/cli.py
k9/cluster_init.py
k9/core.py
k9/deploy.py
k9/exts.py
k9/factsheet.py
k9/helm.py
k9/jcasc.py
k9/rbac.py
k9/storage.py
k9/templates.py
k9/factsheet/prd-service-app-factsheet.md
k9/factsheet/prd-ui-app-factsheet.md
k9/factsheet/service-app-factsheet.md
k9/factsheet/ui-app-factsheet.md
k9/yaml/aws-load-balancer-controller-values.yml
k9/yaml/aws-storage-values.yml
k9/yaml/default-sc.yml
k9/yaml/efk-values.yml
k9/yaml/grafana-values.yml
k9/yaml/jenkins-pvc.yml
k9/yaml/jenkins-values.yml
k9/yaml/prometheus-values.yml
k9/yaml/sonarqube-values.yml
k9/yaml/access-role/access-ClusterRole.yml
k9/yaml/access-role/access-ClusterRoleBinding.yml
k9/yaml/access-role/aws-auth-entry.yml
k9/yaml/autoscaler/deploy.yml
k9/yaml/autoscaler/infra.yml
k9/yaml/cfm/ssm-access.yml
k9/yaml/cfm/promote-service/promote-service-template.yml
k9/yaml/cfm/promote-service/promote-service.py
k9/yaml/cfm/promote-ui/awscli-lambda-layer.zip
k9/yaml/cfm/promote-ui/promote-ui-template.yml
k9/yaml/cfm/promote-ui/promote-ui.py
k9/yaml/ecr-sync/ecr-sync-cj-template.yml
k9/yaml/ecr-sync/ecr-sync-values-template.yml
k9/yaml/grafana/dashboards/kubernetes-cluster-autoscaler.json
k9/yaml/grafana/dashboards/kubernetes-volume-usage-percentage.json
k9/yaml/grafana/dashboards/node-exporter-full.json
k9/yaml/grafana/dashboards/pod-health.json
k9/yaml/grafana/notification-channels/eks-lambda-test.json
k9/yaml/grafana/notification-channels/google-chat-alert.json
k9/yaml/grafana/notification-channels/lambda.json
k9/yaml/grafana/notification-channels/prometheus-alert-manager.json
k9/yaml/grafana/notification-channels/slack-(prometheus-alerts).json
k9/yaml/jenkins/configure-sonarqube.yml
k9/yaml/jenkins/credentials.yml
k9/yaml/jenkins/multibranch-pipeline.yml
k9/yaml/jenkins/secret-text-credentials.yml
k9/yaml/kibana/boiler-api-dashboard.ndjson
k9/yaml/kibana/boiler-dashboard.ndjson
k9/yaml/kibana/boiler-error-dashboard.ndjson
k9-1.0.0.dist-info/METADATA
k9-1.0.0.dist-info/WHEEL
k9-1.0.0.dist-info/dependency_links.txt
k9-1.0.0.dist-info/entry_points.txt
k9-1.0.0.dist-info/top_level.txt
k9-1.0.0.dist-info/RECORD
