Metadata-Version: 2.1
Name: k9
Version: 1.0.0
Summary: Automation Helper for K8 (Kubernetes)
Home-page: https://gitlab.com/python-cicd/k9
Author: SimonComputing, Inc.
Author-email: simon@simoncomputing.com
License: MIT
Platform: UNKNOWN
Classifier: License :: OSI Approved :: MIT License
Classifier: Programming Language :: Python :: 3
Classifier: Programming Language :: Python :: 3.7
Requires-Dist: kubernetes
Requires-Dist: jinja2
Requires-Dist: requests
Requires-Dist: atomic-cloud (==2.0.1)
